dir_content_diff/__init__.py
dir_content_diff/base_comparators.py
dir_content_diff/config.py
dir_content_diff/core.py
dir_content_diff/parallel_utils.py
dir_content_diff/pytest_plugin.py
dir_content_diff/registry.py
dir_content_diff/util.py
dir_content_diff/cli/__init__.py
dir_content_diff/comparators/__init__.py
dir_content_diff/comparators/dependencies.json
dir_content_diff/comparators/morphio.py
dir_content_diff/comparators/pandas.py
dir_content_diff/comparators/voxcell.py
dir_content_diff-1.14.1.dist-info/licenses/AUTHORS.md
dir_content_diff-1.14.1.dist-info/licenses/LICENSE.txt
dir_content_diff-1.14.1.dist-info/METADATA
dir_content_diff-1.14.1.dist-info/WHEEL
dir_content_diff-1.14.1.dist-info/entry_points.txt
dir_content_diff-1.14.1.dist-info/top_level.txt
dir_content_diff-1.14.1.dist-info/RECORD
