Metadata-Version: 2.4
Name: dir-content-diff
Version: 1.14.1
Summary: Simple tool to compare directory contents.
Author: Blue Brain Project, EPFL
License: Apache License 2.0
Project-URL: Homepage, https://dir-content-diff.readthedocs.io
Project-URL: Repository, https://github.com/BlueBrain/dir-content-diff
Project-URL: Tracker, https://github.com/BlueBrain/dir-content-diff/issues
Classifier: Development Status :: 5 - Production/Stable
Classifier: Intended Audience :: Developers
Classifier: License :: OSI Approved :: Apache Software License
Classifier: Programming Language :: Python
Classifier: Programming Language :: Python :: 3
Classifier: Programming Language :: Python :: 3.9
Classifier: Programming Language :: Python :: 3.10
Classifier: Programming Language :: Python :: 3.11
Classifier: Programming Language :: Python :: 3.12
Classifier: Topic :: Software Development :: Libraries :: Python Modules
Requires-Python: >=3.9
License-File: LICENSE.txt
License-File: AUTHORS.md
Requires-Dist: attrs>=21.3.0
Requires-Dist: click>=8
Requires-Dist: dictdiffer>=0.8
Requires-Dist: dicttoxml>=1.7.12
Requires-Dist: diff_pdf_visually>=1.7
Requires-Dist: jsonpath-ng>=1.5
Requires-Dist: packaging>=20
Requires-Dist: PyYaml>=6
Provides-Extra: all-comparators
Requires-Dist: pandas>=1.4; extra == "all-comparators"
Requires-Dist: pyarrow>=11; extra == "all-comparators"
Requires-Dist: tables>=3.7; extra == "all-comparators"
Requires-Dist: morphio>=3.3.6; extra == "all-comparators"
Requires-Dist: morph_tool>=2.9; extra == "all-comparators"
Requires-Dist: voxcell>=3.1.1; extra == "all-comparators"
Requires-Dist: pynrrd<1.1,>=0.4; extra == "all-comparators"
Provides-Extra: docs
Requires-Dist: myst_parser; extra == "docs"
Requires-Dist: sphinx; extra == "docs"
Requires-Dist: furo; extra == "docs"
Provides-Extra: test
Requires-Dist: dicttoxml>=1.7.16; extra == "test"
Requires-Dist: matplotlib>=3.4; extra == "test"
Requires-Dist: rst2pdf>=0.99; extra == "test"
Requires-Dist: pandas>=1.4; extra == "test"
Requires-Dist: pytest>=6.2; extra == "test"
Requires-Dist: pytest-click>=1.1; extra == "test"
Requires-Dist: pytest-console-scripts>=1.4; extra == "test"
Requires-Dist: pytest-cov>=4.1; extra == "test"
Requires-Dist: pytest-html>=3.2; extra == "test"
Provides-Extra: pandas
Requires-Dist: pandas>=1.4; extra == "pandas"
Requires-Dist: pyarrow>=11; extra == "pandas"
Requires-Dist: tables>=3.7; extra == "pandas"
Provides-Extra: morphio
Requires-Dist: morphio>=3.3.6; extra == "morphio"
Requires-Dist: morph_tool>=2.9; extra == "morphio"
Provides-Extra: voxcell
Requires-Dist: voxcell>=3.1.1; extra == "voxcell"
Requires-Dist: pynrrd<1.1,>=0.4; extra == "voxcell"
Dynamic: license-file
Dynamic: provides-extra
